f5project/__init__.py
f5project/helpers.py
f5project/console_scripts/__init__.py
f5project/console_scripts/templates/.gitignore
f5project/console_scripts/templates/README.md
f5project/console_scripts/templates/main.py
f5project/console_scripts/templates/my_strategies.py
f5project/console_scripts/templates/requirements.txt
f5project/console_scripts/templates/.github/workflows/main.yml
f5project/console_scripts/templates/.secrets/index.json
f5project/console_scripts/templates/__pycache__/main.cpython-310.pyc
f5project/console_scripts/templates/__pycache__/my_strategies.cpython-310.pyc
f5project/console_scripts/templates/scripts/setup_github_secrets.py
f5project/console_scripts/templates/scripts/__pycache__/setup_github_secrets.cpython-310.pyc
f5project-0.0.28.dist-info/LICENSE
f5project-0.0.28.dist-info/METADATA
f5project-0.0.28.dist-info/WHEEL
f5project-0.0.28.dist-info/entry_points.txt
f5project-0.0.28.dist-info/top_level.txt
f5project-0.0.28.dist-info/RECORD
