Metadata-Version: 2.1
Name: f5project
Version: 0.0.28
Summary: F5 project
Home-page: https://github.com/thejimmylin/f5project
Author: thejimmylin
Author-email: b00502013@gmail.com
License: UNKNOWN
Platform: UNKNOWN
Classifier: Programming Language :: Python :: 3
Classifier: License :: OSI Approved :: MIT License
Classifier: Operating System :: OS Independent
Requires-Python: >=3.10
License-File: LICENSE
Requires-Dist: finlab (==0.4.5)
Requires-Dist: fugle-trade (==0.4.0)
Requires-Dist: python-dotenv (==1.0.0)
Requires-Dist: functions-framework (==3.4.0)
Requires-Dist: loguru (==0.7.0)
Requires-Dist: github-secret-syncer (==0.0.10)
